{
  "My Iron Nut": 1315,
  "TigerShrimp": 836,
  "4k cox": 500,
  "TF Silent": 500,
  "Busty GIM": 1630,
  "Matthew99143": 400,
  "Sour Cherry": 405,
  "Yost": 710,
  "basic drip": 565,
  "DePonies": 440,
  "og unethical": 1505,
  "SaintVersi": 280,
  "sx_m": 280,
  "thedumper": 380,
  "Tryedge1": 500,
  "IM Cake": 1015,
  "Arsid": 600,
  "The lil iron": 440,
  "Papa Rose": 15,
  "MF Jones 1": 850,
  "bippur": 50,
  "JellyOfMyGim": 200,
  "Stiigz": 5,
  "Screwcats": 100,
  "Drippy Drizz": 30,
  "D4MONR": 110,
  "Rs Thug Life": 30,
  "Jellyofmyely": 60,
  "Blowmygim": 30,
  "Donkeykick8": 30,
  "htsridas856": 400,
  "screwkats": 60,
  "Sumatra Ters": 210,
  "LietGhost": 100,
  "Dicingvega": 330,
  "Extracredit0": 10,
  "Vi o": 10,
  "Ruhan21": 30,
  "TheMrAgony": 10
}